iot_device/__init__.py
iot_device/all.py
iot_device/certificate.py
iot_device/device.py
iot_device/device_config.py
iot_device/device_registry.py
iot_device/device_server.py
iot_device/discover.py
iot_device/discover_broadcasts.py
iot_device/discover_mdns.py
iot_device/discover_serial.py
iot_device/env.py
iot_device/eval.py
iot_device/eval_file_ops.py
iot_device/eval_rlist.py
iot_device/eval_rsync.py
iot_device/mp_device.py
iot_device/mp_protocol.py
iot_device/pyboard.py
iot_device/pydevice.py
iot_device/repl_protocol.py
iot_device/secrets.py
iot_device/serial_device.py
iot_device/telnet_device.py
iot_device/utilities.py
iot_device/version.py
iot_device/webrepl_device.py
iot_device-0.5.32.dist-info/LICENSE.txt
iot_device-0.5.32.dist-info/METADATA
iot_device-0.5.32.dist-info/WHEEL
iot_device-0.5.32.dist-info/top_level.txt
iot_device-0.5.32.dist-info/zip-safe
iot_device-0.5.32.dist-info/RECORD
