Metadata-Version: 2.1
Name: iot-device
Version: 0.5.32
Summary: MicroPython REPL Interface
Home-page: https://github.com/iot49/iot-device
Author: Bernhard Boser
License: MIT
Keywords: MicroPython,Repl
Classifier: Development Status :: 3 - Alpha
Classifier: License :: OSI Approved :: MIT License
Classifier: Programming Language :: Python
Requires-Python: >=3.7
License-File: LICENSE.txt
Requires-Dist: pyserial
Requires-Dist: termcolor
Requires-Dist: pyopenssl
Requires-Dist: zeroconf
Requires-Dist: websocket-client
Requires-Dist: pyyaml
